[{"C_24aa6558a576445e96a3fbe1e1aedc30": {"0": "human", "1": "rule_bot"}, "C_3aadb8a5a4084e5f8ab3bbd6f219a2a6": {"0": "human", "1": "rule_bot"}, "C_e0827f9b3ed140068ade358df2b8a454": {"0": "human", "1": "rule_bot"}, "C_6d4ed28633c44cb584c5a79dff5a2f9c": {"0": "rule_bot", "1": "human"}, "C_3bfd6ed35c6d4530a377f77cdd120c0e": {"0": "human", "1": "rule_bot"}, "C_25425a1642a74e4ab2c4c21b8813ab07": {"0": "rule_bot", "1": "human"}, "C_1678d85f82be4b3f866d3b83674a2e38": {"0": "human", "1": "rule_bot"}, "C_ec2890e0c43b4b5392690ad4084b07a5": {"0": "human", "1": "rule_bot"}, "C_c5b3d1c199884a2282d444accd684d0c": {"0": "human", "1": "rule_bot"}, "C_64a033430b3a4095942fe71429e53a44": {"0": "human", "1": "rule_bot"}, "C_a964ec9f6e4a40859a55a09380bbe621": {"0": "rule_bot", "1": "human"}, "C_c64ffaeadf4d465db8de061c90836863": {"0": "rule_bot", "1": "human"}, "C_ea03cdc825f349ab9216c31a0985cb6f": {"0": "rule_bot", "1": "human"}, "C_5664f5bd49254d3682a74964b606859b": {"0": "rule_bot", "1": "human"}, "C_9a6ba0b6db5e419ca2a26d7c794538fe": {"0": "rule_bot", "1": "human"}, "C_925790880a2c47148a80d76e1332042b": {"0": "human", "1": "rule_bot"}, "C_580c2051cdeb4154b8073e724e7a4b9c": {"0": "rule_bot", "1": "human"}, "C_67dc20625718465eadb42e5768574240": {"0": "human", "1": "rule_bot"}, "C_ed78e4c50556419c95774e9c0db9f7aa": {"0": "human", "1": "rule_bot"}, "C_050b8631ab1d4e599ebe8f38b096ae21": {"0": "rule_bot", "1": "human"}, "C_468c992e563149d7bfcbefd95f866610": {"0": "rule_bot", "1": "human"}, "C_6a49e5ab6a24463e963e5de4b42536f9": {"0": "rule_bot", "1": "human"}, "C_1eb8ca9c14194b7a870ea0ee8e7e1579": {"0": "human", "1": "rule_bot"}, "C_8dc71d3ea0f145f7a80e38b4e0a38859": {"0": "human", "1": "rule_bot"}, "C_7e5ca27066124b66b9359e5865fe9f55": {"0": "rule_bot", "1": "human"}, "C_f90ea28e18fa47a69768052107dedc11": {"0": "rule_bot", "1": "human"}}, {"C_24aa6558a576445e96a3fbe1e1aedc30": {"0": {}, "1": {"n00_gender": "f", "n01_i_understand": 5, "n02_cooperative": 5, "n03_human": 5, "n04_understand_me": 5, "n05_chat": 5, "n06_texts": 4, "n07_tech": 5, "n08_learn_spa": 3, "n09_learn_eng": 2, "n10_age": 2, "n11_ability_spa": 3, "n12_ability_eng": 5, "n13_country": 4, "n14_online_spa": 2, "n15_online_eng": 9, "n16_online_mix": 1, "n17_comments": "", "n18_non_native": "1", "n19_partner_gender": "m", "n20_languages": "1,2,6", "n21_education": "4"}, "worker": "A3DTLM6EVD4EVV"}, "C_3aadb8a5a4084e5f8ab3bbd6f219a2a6": {"0": {}, "1": {"n00_gender": "m", "n01_i_understand": 5, "n02_cooperative": 4, "n03_human": 5, "n04_understand_me": 5, "n05_chat": 5, "n06_texts": 5, "n07_tech": 5, "n08_learn_spa": 1, "n09_learn_eng": 1, "n10_age": 1, "n11_ability_spa": 5, "n12_ability_eng": 5, "n13_country": 4, "n14_online_spa": 0, "n15_online_eng": 8, "n16_online_mix": 2, "n17_comments": "One way this platform could be improved is if the time restriction between selecting the friends was increased. With 8 minutes in total available to chat, and each restriction between selecting the friends being just 10 seconds, the participants can just spam select the friends, and not have a meaningful conversation.", "n18_non_native": "1", "n19_partner_gender": "m", "n20_languages": "1,2,12", "n21_education": "2"}, "worker": "A30Z3CWKO1B6R7"}, "C_e0827f9b3ed140068ade358df2b8a454": {"0": {}, "1": {"n00_gender": "f", "n01_i_understand": 5, "n02_cooperative": 5, "n03_human": 5, "n04_understand_me": 5, "n05_chat": 5, "n06_texts": 1, "n07_tech": 5, "n08_learn_spa": 1, "n09_learn_eng": 1, "n10_age": 2, "n11_ability_spa": 5, "n12_ability_eng": 5, "n13_country": 4, "n14_online_spa": 1, "n15_online_eng": 10, "n16_online_mix": 2, "n17_comments": "", "n18_non_native": "5", "n19_partner_gender": "m", "n20_languages": "1,2", "n21_education": "4"}, "worker": "A2BO8M77CS3SGZ"}, "C_6d4ed28633c44cb584c5a79dff5a2f9c": {"0": {"n00_gender": "m", "n01_i_understand": 5, "n02_cooperative": 3, "n03_human": 3, "n04_understand_me": 1, "n05_chat": 4, "n06_texts": 2, "n07_tech": 4, "n08_learn_spa": 1, "n09_learn_eng": 3, "n10_age": 3, "n11_ability_spa": 5, "n12_ability_eng": 5, "n13_country": 4, "n14_online_spa": 3, "n15_online_eng": 7, "n16_online_mix": 5, "n17_comments": "", "n18_non_native": "3", "n19_partner_gender": "m", "n20_languages": "1,2,12", "n21_education": "3"}, "1": {}, "worker": "A2EV4VW1L9KDB1"}, "C_3bfd6ed35c6d4530a377f77cdd120c0e": {"0": {}, "1": {"n00_gender": "m", "n01_i_understand": 5, "n02_cooperative": 4, "n03_human": 3, "n04_understand_me": 3, "n05_chat": 4, "n06_texts": 3, "n07_tech": 4, "n08_learn_spa": 1, "n09_learn_eng": 3, "n10_age": 3, "n11_ability_spa": 5, "n12_ability_eng": 5, "n13_country": 4, "n14_online_spa": 3, "n15_online_eng": 7, "n16_online_mix": 5, "n17_comments": "", "n18_non_native": "3", "n19_partner_gender": "m", "n20_languages": "1,2,12", "n21_education": "3"}, "worker": "A2EV4VW1L9KDB1"}, "C_25425a1642a74e4ab2c4c21b8813ab07": {"0": {"n00_gender": "m", "n01_i_understand": 5, "n02_cooperative": 4, "n03_human": 3, "n04_understand_me": 3, "n05_chat": 4, "n06_texts": 3, "n07_tech": 4, "n08_learn_spa": 1, "n09_learn_eng": 3, "n10_age": 3, "n11_ability_spa": 5, "n12_ability_eng": 5, "n13_country": 4, "n14_online_spa": 3, "n15_online_eng": 7, "n16_online_mix": 5, "n17_comments": "", "n18_non_native": "3", "n19_partner_gender": "m", "n20_languages": "1,2,12", "n21_education": "3"}, "1": {}, "worker": "A2EV4VW1L9KDB1"}, "C_1678d85f82be4b3f866d3b83674a2e38": {"0": {}, "1": {"n00_gender": "f", "n01_i_understand": 4, "n02_cooperative": 4, "n03_human": 4, "n04_understand_me": 4, "n05_chat": 4, "n06_texts": 4, "n07_tech": 4, "n08_learn_spa": 3, "n09_learn_eng": 2, "n10_age": 4, "n11_ability_spa": 4, "n12_ability_eng": 5, "n13_country": 4, "n14_online_spa": 7, "n15_online_eng": 4, "n16_online_mix": 8, "n17_comments": "interesting work", "n18_non_native": "3", "n19_partner_gender": "o", "n20_languages": "1,2,11", "n21_education": "4"}, "worker": "A4806MFWRDL42"}, "C_ec2890e0c43b4b5392690ad4084b07a5": {"0": {}, "1": {"n00_gender": "f", "n01_i_understand": 4, "n02_cooperative": 4, "n03_human": 4, "n04_understand_me": 4, "n05_chat": 4, "n06_texts": 4, "n07_tech": 4, "n08_learn_spa": 3, "n09_learn_eng": 2, "n10_age": 4, "n11_ability_spa": 4, "n12_ability_eng": 4, "n13_country": 4, "n14_online_spa": 7, "n15_online_eng": 5, "n16_online_mix": 8, "n17_comments": "interesting work", "n18_non_native": "3", "n19_partner_gender": "o", "n20_languages": "1,2,11", "n21_education": "4"}, "worker": "A4806MFWRDL42"}, "C_c5b3d1c199884a2282d444accd684d0c": {"0": {}, "1": {"n00_gender": "m", "n01_i_understand": 5, "n02_cooperative": 4, "n03_human": 4, "n04_understand_me": 4, "n05_chat": 4, "n06_texts": 4, "n07_tech": 5, "n08_learn_spa": 2, "n09_learn_eng": 2, "n10_age": 2, "n11_ability_spa": 3, "n12_ability_eng": 4, "n13_country": 4, "n14_online_spa": 5, "n15_online_eng": 7, "n16_online_mix": 6, "n17_comments": "Thanks for the survey", "n18_non_native": "4", "n19_partner_gender": "m", "n20_languages": "1,2,3,6", "n21_education": "3"}, "worker": "A8DFFGPH3G3V5"}, "C_64a033430b3a4095942fe71429e53a44": {"0": {}, "1": {"n00_gender": "m", "n01_i_understand": 4, "n02_cooperative": 4, "n03_human": 2, "n04_understand_me": 2, "n05_chat": 4, "n06_texts": 4, "n07_tech": 4, "n08_learn_spa": 1, "n09_learn_eng": 2, "n10_age": 3, "n11_ability_spa": 5, "n12_ability_eng": 4, "n13_country": 4, "n14_online_spa": 6, "n15_online_eng": 7, "n16_online_mix": 4, "n17_comments": "thanks", "n18_non_native": "4", "n19_partner_gender": "m", "n20_languages": "1,2,3,5", "n21_education": "4"}, "worker": "ARTQWWNFA7IOD"}, "C_a964ec9f6e4a40859a55a09380bbe621": {"0": {"n00_gender": "f", "n01_i_understand": 5, "n02_cooperative": 3, "n03_human": 3, "n04_understand_me": 2, "n05_chat": 4, "n06_texts": 2, "n07_tech": 4, "n08_learn_spa": 1, "n09_learn_eng": 1, "n10_age": 1, "n11_ability_spa": 5, "n12_ability_eng": 5, "n13_country": 4, "n14_online_spa": 2, "n15_online_eng": 8, "n16_online_mix": 3, "n17_comments": "Occasionally, I think my partner may have been confused about what I was saying as they didn't seem to acknowledge some of the things I said and instead continued to ask me questions ", "n18_non_native": "4", "n19_partner_gender": "m", "n20_languages": "1,2,12", "n21_education": "2"}, "1": {}, "worker": "A2ZIO0ZTIXOE9J"}, "C_c64ffaeadf4d465db8de061c90836863": {"0": {"n00_gender": "m", "n01_i_understand": 5, "n02_cooperative": 5, "n03_human": 5, "n04_understand_me": 5, "n05_chat": 5, "n06_texts": 4, "n07_tech": 5, "n08_learn_spa": 1, "n09_learn_eng": 2, "n10_age": 2, "n11_ability_spa": 5, "n12_ability_eng": 4, "n13_country": 4, "n14_online_spa": 7, "n15_online_eng": 3, "n16_online_mix": 7, "n17_comments": "", "n18_non_native": "4", "n19_partner_gender": "m", "n20_languages": "1,2", "n21_education": "4"}, "1": {}, "worker": "A3V5PLGA683JJF"}, "C_ea03cdc825f349ab9216c31a0985cb6f": {"0": {"n00_gender": "f", "n01_i_understand": 4, "n02_cooperative": 4, "n03_human": 1, "n04_understand_me": 2, "n05_chat": 2, "n06_texts": 1, "n07_tech": 2, "n08_learn_spa": 6, "n09_learn_eng": 1, "n10_age": 1, "n11_ability_spa": 2, "n12_ability_eng": 5, "n13_country": 1, "n14_online_spa": 1, "n15_online_eng": 9, "n16_online_mix": 0, "n17_comments": "I speak better than I write in Hindu- It took more time that i would have liked to respond.", "n18_non_native": "3", "n19_partner_gender": "m", "n20_languages": "1,2,14", "n21_education": "3"}, "1": {}, "worker": "A20M7MAG6N0C4D"}, "C_5664f5bd49254d3682a74964b606859b": {"0": {"n00_gender": "m", "n01_i_understand": 5, "n02_cooperative": 1, "n03_human": 1, "n04_understand_me": 4, "n05_chat": 1, "n06_texts": 5, "n07_tech": 2, "n08_learn_spa": 2, "n09_learn_eng": 2, "n10_age": 1, "n11_ability_spa": 3, "n12_ability_eng": 5, "n13_country": 1, "n14_online_spa": 0, "n15_online_eng": 10, "n16_online_mix": 0, "n17_comments": "", "n18_non_native": "5", "n19_partner_gender": "m", "n20_languages": "1,2,8", "n21_education": "2"}, "1": {}, "worker": "A32KO4VDUAKQKB"}, "C_9a6ba0b6db5e419ca2a26d7c794538fe": {"0": {"n00_gender": "m", "n01_i_understand": 4, "n02_cooperative": 4, "n03_human": 3, "n04_understand_me": 4, "n05_chat": 3, "n06_texts": 4, "n07_tech": 5, "n08_learn_spa": 1, "n09_learn_eng": 2, "n10_age": 3, "n11_ability_spa": 5, "n12_ability_eng": 5, "n13_country": 4, "n14_online_spa": 1, "n15_online_eng": 6, "n16_online_mix": 3, "n17_comments": "The respondent only communicated in English, If it was to be in Hinglish then the reply should have been in Hinglish.", "n18_non_native": "2", "n19_partner_gender": "m", "n20_languages": "1,2,8,9", "n21_education": "3"}, "1": {}, "worker": "A2R6EIJYKZGUN8"}, "C_925790880a2c47148a80d76e1332042b": {"0": {}, "1": {"n00_gender": "m", "n01_i_understand": 3, "n02_cooperative": 2, "n03_human": 2, "n04_understand_me": 2, "n05_chat": 4, "n06_texts": 2, "n07_tech": 4, "n08_learn_spa": 1, "n09_learn_eng": 2, "n10_age": 2, "n11_ability_spa": 5, "n12_ability_eng": 5, "n13_country": 4, "n14_online_spa": 3, "n15_online_eng": 7, "n16_online_mix": 5, "n17_comments": "bot does not seem lifelike yet.", "n18_non_native": "4", "n19_partner_gender": "o", "n20_languages": "1,2,7", "n21_education": "4"}, "worker": "A22ZC69DOMCUNY"}, "C_580c2051cdeb4154b8073e724e7a4b9c": {"0": {"n00_gender": "m", "n01_i_understand": 4, "n02_cooperative": 4, "n03_human": 4, "n04_understand_me": 4, "n05_chat": 4, "n06_texts": 1, "n07_tech": 1, "n08_learn_spa": 2, "n09_learn_eng": 2, "n10_age": 1, "n11_ability_spa": 3, "n12_ability_eng": 5, "n13_country": 1, "n14_online_spa": 0, "n15_online_eng": 10, "n16_online_mix": 0, "n17_comments": "", "n18_non_native": "4", "n19_partner_gender": "m", "n20_languages": "1,2", "n21_education": "2"}, "1": {}, "worker": "A32KO4VDUAKQKB"}, "C_67dc20625718465eadb42e5768574240": {"0": {}, "1": {"n00_gender": "f", "n01_i_understand": 4, "n02_cooperative": 4, "n03_human": 3, "n04_understand_me": 4, "n05_chat": 2, "n06_texts": 2, "n07_tech": 4, "n08_learn_spa": 5, "n09_learn_eng": 3, "n10_age": 3, "n11_ability_spa": 4, "n12_ability_eng": 5, "n13_country": 2, "n14_online_spa": 1, "n15_online_eng": 6, "n16_online_mix": 1, "n17_comments": "the bot only wrote in English", "n18_non_native": "4", "n19_partner_gender": "m", "n20_languages": "1,2,12,14", "n21_education": "4"}, "worker": "AJZ9CVVRE2E30"}, "C_ed78e4c50556419c95774e9c0db9f7aa": {"0": {}, "1": {"n00_gender": "f", "n01_i_understand": 5, "n02_cooperative": 4, "n03_human": 3, "n04_understand_me": 4, "n05_chat": 2, "n06_texts": 3, "n07_tech": 4, "n08_learn_spa": 5, "n09_learn_eng": 3, "n10_age": 3, "n11_ability_spa": 4, "n12_ability_eng": 5, "n13_country": 2, "n14_online_spa": 1, "n15_online_eng": 6, "n16_online_mix": 2, "n17_comments": "", "n18_non_native": "4", "n19_partner_gender": "m", "n20_languages": "1,2,12,14", "n21_education": "4"}, "worker": "AJZ9CVVRE2E30"}, "C_050b8631ab1d4e599ebe8f38b096ae21": {"0": {"n00_gender": "f", "n01_i_understand": 3, "n02_cooperative": 4, "n03_human": 3, "n04_understand_me": 3, "n05_chat": 3, "n06_texts": 3, "n07_tech": 3, "n08_learn_spa": 1, "n09_learn_eng": 2, "n10_age": 1, "n11_ability_spa": 5, "n12_ability_eng": 5, "n13_country": 4, "n14_online_spa": 5, "n15_online_eng": 5, "n16_online_mix": 9, "n17_comments": "the partner was very co-operative and patient ...", "n18_non_native": "2", "n19_partner_gender": "m", "n20_languages": "1,2,3,5", "n21_education": "2"}, "1": {}, "worker": "AJZ9CVVRE2E30"}, "C_468c992e563149d7bfcbefd95f866610": {"0": {"n00_gender": "f", "n01_i_understand": 4, "n02_cooperative": 4, "n03_human": 3, "n04_understand_me": 4, "n05_chat": 3, "n06_texts": 3, "n07_tech": 4, "n08_learn_spa": 2, "n09_learn_eng": 3, "n10_age": 4, "n11_ability_spa": 5, "n12_ability_eng": 4, "n13_country": 4, "n14_online_spa": 3, "n15_online_eng": 4, "n16_online_mix": 3, "n17_comments": "", "n18_non_native": "2", "n19_partner_gender": "m", "n20_languages": "1,2,3,9", "n21_education": "3"}, "1": {}, "worker": "A2CWBA5KCB6BUB"}, "C_6a49e5ab6a24463e963e5de4b42536f9": {"0": {"n00_gender": "f", "n01_i_understand": 5, "n02_cooperative": 4, "n03_human": 3, "n04_understand_me": 4, "n05_chat": 2, "n06_texts": 3, "n07_tech": 4, "n08_learn_spa": 3, "n09_learn_eng": 3, "n10_age": 3, "n11_ability_spa": 3, "n12_ability_eng": 5, "n13_country": 2, "n14_online_spa": 3, "n15_online_eng": 5, "n16_online_mix": 2, "n17_comments": "", "n18_non_native": "3", "n19_partner_gender": "m", "n20_languages": "1,2,14", "n21_education": "4"}, "1": {}, "worker": "AJZ9CVVRE2E30"}, "C_1eb8ca9c14194b7a870ea0ee8e7e1579": {"0": {}, "1": {"n00_gender": "f", "n01_i_understand": 5, "n02_cooperative": 5, "n03_human": 4, "n04_understand_me": 5, "n05_chat": 5, "n06_texts": 4, "n07_tech": 4, "n08_learn_spa": 1, "n09_learn_eng": 1, "n10_age": 5, "n11_ability_spa": 5, "n12_ability_eng": 5, "n13_country": 4, "n14_online_spa": 3, "n15_online_eng": 8, "n16_online_mix": 4, "n17_comments": "it was a good task\n", "n18_non_native": "2", "n19_partner_gender": "m", "n20_languages": "1,2,11", "n21_education": "3"}, "worker": "AYPG99OS2IVLA"}, "C_8dc71d3ea0f145f7a80e38b4e0a38859": {"0": {}, "1": {"n00_gender": "m", "n01_i_understand": 3, "n02_cooperative": 4, "n03_human": 4, "n04_understand_me": 4, "n05_chat": 4, "n06_texts": 4, "n07_tech": 4, "n08_learn_spa": 1, "n09_learn_eng": 1, "n10_age": 3, "n11_ability_spa": 3, "n12_ability_eng": 4, "n13_country": 4, "n14_online_spa": 3, "n15_online_eng": 5, "n16_online_mix": 2, "n17_comments": "I was curious about the experiment and wanted to try it out, it was interesting. the platform is good.", "n18_non_native": "2", "n19_partner_gender": "f", "n20_languages": "1,2,4,14", "n21_education": "3"}, "worker": "AO2SEJOUWKOCV"}, "C_7e5ca27066124b66b9359e5865fe9f55": {"0": {"n00_gender": "m", "n01_i_understand": 3, "n02_cooperative": 4, "n03_human": 3, "n04_understand_me": 2, "n05_chat": 2, "n06_texts": 2, "n07_tech": 4, "n08_learn_spa": 2, "n09_learn_eng": 2, "n10_age": 2, "n11_ability_spa": 4, "n12_ability_eng": 4, "n13_country": 4, "n14_online_spa": 2, "n15_online_eng": 7, "n16_online_mix": 5, "n17_comments": "In starting i was a bit confused what exactly we have to do, but later i understood how this task works. Sorry for the mistakes i made.", "n18_non_native": "3", "n19_partner_gender": "o", "n20_languages": "1,2", "n21_education": "3"}, "1": {}, "worker": "A1WAC863OL2I3S"}, "C_f90ea28e18fa47a69768052107dedc11": {"0": {"n00_gender": "f", "n01_i_understand": 4, "n02_cooperative": 4, "n03_human": 4, "n04_understand_me": 5, "n05_chat": 4, "n06_texts": 2, "n07_tech": 2, "n08_learn_spa": 2, "n09_learn_eng": 1, "n10_age": 1, "n11_ability_spa": 5, "n12_ability_eng": 5, "n13_country": 1, "n14_online_spa": 1, "n15_online_eng": 9, "n16_online_mix": 0, "n17_comments": "", "n18_non_native": "3", "n19_partner_gender": "m", "n20_languages": "1,2,4,12", "n21_education": "3"}, "1": {}, "worker": "A30HB9YQHJ8UUJ"}}]